Workbook

Sheet README
A1: Cartographie des risques – Assurance santé (version réaliste, fictive)
A3: Objectif | B3: Fournir un registre de risques sectoriel crédible pour un organisme complémentaire d'assurance santé / mutuelle / assureur santé opérant en France. Le fichier est fictif mais construit à partir de risques et contrôles typiques du secteur.
A4: Ce que contient le classeur | B4: 1) un registre détaillé de 120 risques ; 2) un dictionnaire des champs ; 3) une méthodologie de scoring ; 4) une synthèse ; 5) une liste de sources réglementaires et sectorielles officielles.
A5: Périmètre sectoriel modélisé | B5: Souscription, pilotage technique, prestations, relation adhérents, tiers payant / flux NOEMIE, réseau de soins, cotisations, ORSA / Solvabilité II, conformité / DDA / fraude, données de santé / RGPD, applications cœur / cybersécurité.
A6: Comment lire le registre | B6: Les colonnes Probabilité/Impact bruts mesurent le risque avant contrôle. Les colonnes résiduelles mesurent le risque après prise en compte des contrôles clés. Le statut vs appétit compare le score résiduel à un seuil d'appétit (Faible=6, Modéré=9, Élevé=12).
A7: Niveau de réalisme | B7: Les scénarios, causes, contrôles, KRI et impacts ont été sectorisés. Les montants, incidents et populations affectées restent synthétiques et ne constituent pas des données observées.
A8: Sources utilisées pour le cadrage | B8: Voir la feuille Sources. Les structures de risques se fondent notamment sur Solvabilité II / ORSA, la gouvernance d'assurance, la DDA, le RGPD appliqué à la santé et la norme NOEMIE.
A11: Feuilles
A12: README
A13: Methodologie
A14: Dictionnaire
A15: Sources
A16: Registre_Risques
A17: Synthese

Sheet Methodologie
A1: Méthodologie de construction du dataset
A3: Bloc | B3: Champ | C3: Règle | D3: Commentaire | E3: Source / Référence
A4: Périmètre | B4: Organisme modélisé | C4: OCAM / mutuelle / assureur santé français | D4: Le périmètre combine assurance santé, réseau de soins, NOEMIE, DDA, RGPD, Solvabilité II. | E4: Voir feuille Sources
A5: Granularité | B5: Nombre de risques | C5: 120 risques | D5: Structure volumique proche d'un registre RCSA intermédiaire/centralisé. | E5: Interne (dataset fictif)
A6: Notation | B6: Probabilité / Impact | C6: Échelle 1 à 5 | D6: 1=faible/rare ; 5=critique/quasi certaine. | E6: Bonne pratique risk management
A7: Formule | B7: Score brut | C7: Probabilité brute x Impact brut | D7: Calcul automatique par formule. | E7: Interne
A8: Formule | B8: Score résiduel | C8: Probabilité résiduelle x Impact résiduel | D8: Calcul automatique par formule. | E8: Interne
A9: Appétit | B9: Seuils | C9: Faible=6 ; Modéré=9 ; Élevé=12 | D9: Utilisé pour Statut vs appétit. | E9: Interne
A10: Réglementaire | B10: Solvabilité II / ORSA | C10: Pilotage prudentiel, gouvernance, contrôle interne, reporting | D10: Particulièrement pertinent pour les risques prudentiels / gouvernance. | E10: ACPR / EIOPA
A11: Réglementaire | B11: DDA | C11: Distribution, devoir de conseil, gouvernance produit | D11: Pertinent pour souscription/distribution/réclamations. | E11: ACPR
A12: Réglementaire | B12: RGPD / données de santé | C12: Licéité, minimisation, habilitations, conservation | D12: Pertinent pour données santé et justificatifs. | E12: CNIL
A13: Réglementaire | B13: NOEMIE / télétransmission | C13: Échanges techniques assurance maladie / complémentaire | D13: Pertinent pour tiers payant et rejets de flux. | E13: Ameli
A14: Construction | B14: KRI | C14: Un KRI par risque | D14: Seuils vert/orange/rouge selon type de risque. | E14: Interne
A15: Construction | B15: Impacts | C15: Financier + conformité + client + opérationnel | D15: Libellés qualitatifs ; pertes 12m synthétiques en EUR. | E15: Interne

Sheet Dictionnaire
A1: Champ | B1: Définition | C1: Type | D1: Exemple
A2: Risk_ID | B2: Identifiant unique du risque | C2: Texte | D2: RSH-001
A3: Direction | B3: Grande direction métier | C3: Liste | D3: Prestations & Relation Adhérents
A4: Processus | B4: Processus de niveau 1 | C4: Liste | D4: Gestion des prestations et remboursements
A5: Sous_processus | B5: Activité ou sous-processus détaillé | C5: Texte | D5: Paiement des prestations
A6: Process_Owner | B6: Responsable métier du processus | C6: Texte | D6: Directeur Prestations Santé
A7: Risk_Owner | B7: Responsable du pilotage du risque | C7: Texte | D7: Directeur Prestations
A8: Control_Owner | B8: Responsable du contrôle clé | C8: Texte | D8: Responsable Paiements Prestations
A9: Famille_de_risque | B9: Typologie du risque | C9: Liste | D9: Données / SI / Cyber
A10: Theme_reglementaire | B10: Référentiel principal associé | C10: Texte | D10: RGPD / sécurité / continuité
A11: Description_du_risque | B11: Formulation concise du risque | C11: Texte | D11: Indisponibilité majeure impactant Paiement des prestations
A12: Scenario_de_risque | B12: Exemple d'occurrence sectorielle | C12: Texte | D12: Rupture de télétransmission ou cyberincident...
... A47: Commentaire_dataset | B47: Mention sur le caractère fictif | C47: Texte | D47: Risque synthétique fictif...

Sheet Sources
A1: Organisme | B1: Sujet | C1: URL | D1: Utilisation dans le dataset
A2: ACPR | B2: Solvabilité II | C2: https://acpr.banque-france.fr/fr/reglementation/focus-sur-la-reglementation/assurance/solvabilite-ii | D2: Cadre prudentiel global des assureurs (pilier 1/2/3).
A3: ACPR | B3: Pilier 2 : gouvernance | C3: https://acpr.banque-france.fr/fr/reglementation/focus-sur-la-reglementation/assurance/solvabilite-ii/pilier-2-la-gouvernance | D3: Gouvernance, gestion des risques et contrôle interne.
A4: ACPR | B4: Pilier 2 : ORSA | C4: https://acpr.banque-france.fr/fr/reglementation/focus-sur-la-reglementation/assurance/solvabilite-ii/pilier-2-levaluation-interne-des-risques-et-de-la-solvabilite | D4: Processus ORSA et pilotage de solvabilité.
A5: EIOPA | B5: Solvency II overview | C5: https://www.eiopa.europa.eu/browse/regulation-and-policy/solvency-ii_en | D5: Référentiel européen prudentiel.
A6: EIOPA | B6: System of governance | C6: https://www.eiopa.europa.eu/rulebook/solvency-ii-single-rulebook/article-2633_en | D6: Exigences détaillées sur système de gouvernance, conformité et audit interne.
A7: CNIL | B7: Données de santé - formalités | C7: https://www.cnil.fr/fr/quelles-formalites-pour-les-traitements-de-donnees-de-sante | D7: Traitement des données de santé : principes et exceptions.
A8: CNIL | B8: RGPD appliqué au secteur de la santé | C8: https://www.cnil.fr/fr/le-rgpd-applique-au-secteur-de-la-sante | D8: Enjeux de protection des données dans la santé.
A9: CNIL | B9: Secteur de l’assurance | C9: https://www.cnil.fr/fr/assurance | D9: Spécificités assurance et données personnelles.
A10: CNIL | B10: Analyse juridique OCAM / données de santé | C10: https://www.cnil.fr/sites/cnil/files/atoms/files/analyse_juridique_adressee_aux_organismes_de_complementaire_sante.pdf | D10: Contraintes autour des justificatifs et remboursements OCAM.
A11: ACPR | B11: DDA | C11: https://acpr.banque-france.fr/la-directive-distribution-en-assurance-dda | D11: Distribution d’assurance, gouvernance produit, devoir de conseil.
A12: ACPR | B12: Recommandation DDA | C12: https://acpr.banque-france.fr/fr/publications-et-statistiques/publications/lacpr-emet-une-recommandation-sur-la-mise-en-oeuvre-de-certaines-dispositions-issues-de-la-directive | D12: Application opérationnelle de la DDA.
... A15: ameli | B15: Le retour NOEMIE | C15: https://www.ameli.fr/professionnel-de-la-lpplatm/exercice-professionnel/facturation/teletransmission-retour-noemie/retour-noemie | D15: Retours et rejets NOEMIE.

Sheet Registre_Risques
A1: Risk_ID | B1: Direction | C1: Processus | D1: Sous_processus | E1: Process_Owner | F1: Risk_Owner | G1: Control_Owner | H1: Famille_de_risque | I1: Theme_reglementaire | J1: Description_du_risque | K1: Scenario_de_risque | L1: Cause_racine | M1: Consequences_potentielles | N1: KRI_nom | O1: Unite_KRI | P1: Seuil_vert | Q1: Seuil_orange | R1: Seuil_rouge | S1: Valeur_actuelle_KRI | T1: Probabilite_brute | U1: Impact_brut | V1: Score_brut | W1: Niveau_brut | X1: Controle_cle | Y1: Type_de_controle | Z1: Frequence_controle | AA1: Efficacite_controle | AB1: Probabilite_residuelle | AC1: Impact_residuel | AD1: Score_residuel | AE1: Niveau_residuel | AF1: Appetit_au_risque | AG1: Statut_vs_appetit | AH1: Strategie_de_traitement | AI1: Plan_d_action | AJ1: Action_owner | AK1: Echeance_action | AL1: Statut_action | AM1: Derniere_revue | AN1: Frequence_revue | AO1: Incidents_12m | AP1: Pertes_12m_EUR | AQ1: Population_affectee_potentielle | AR1: Reference_reglementaire | AS1: Justification_sectorielle | AT1: Commentaire_dataset
A2: RSH-001 | B2: Souscription & Pilotage Produit | C2: Tarification et pilotage technique santé | D2: Construction des barèmes | E2: Directeur Technique Santé | F2: Directeur Technique / Actuariat | G2: Responsable Actuariat Santé | H2: Opérationnel / Qualité | I2: Contrôle interne / Qualité de service | J2: Erreur d'exécution ou de paramétrage sur Construction des barèmes | K2: Hausse des dépenses optiques/dentaires non intégrée à temps dans le barème et dérive du ratio technique. | L2: Procédure incomplète, charge mal calibrée, contrôle de 1er niveau insuffisant ou règle métier mal paramétrée | M2: Retards, retraitements, mauvaise qualité de service, hausse du coût de gestion et insatisfaction adhérents/entreprises | N2: Taux d'anomalies opérationnelles sur Construction des barèmes | O2: % | P2: 1 | Q2: 2.5 | R2: 4 | S2: 2 | T2: 3 | U2: 4 | V2: =T2*U2 -> 12 | W2: =IF(V2>=15,"Critique",IF(V2>=10,"Élevé",IF(V2>=6,"Modéré","Faible"))) -> Élevé | X2: Double validation, check-list opératoire, rapprochement quotidien et contrôle de cohérence | Y2: Préventif | Z2: Mensuelle | AA2: Moyenne | AB2: 2 | AC2: 4 | AD2: =AB2*AC2 -> 8 | AE2: =IF(AD2>=15,"Critique",IF(AD2>=10,"Élevé",IF(AD2>=6,"Modéré","Faible"))) -> Modéré | AF2: Modéré | AG2: =IF(AD2<=IF(AF2="Faible",6,IF(AF2="Modéré",9,12)),"Dans lappétit","Hors appétit") -> Dans lappétit | AH2: Réduire | AI2: Formaliser les points de contrôle critiques, renforcer les rapprochements et fiabiliser les règles métier sur construction des barèmes. | AJ2: Responsable Actuariat Santé | AK2: 46138 | AL2: À lancer | AM2: 46076 | AN2: Semestrielle | AO2: 3 | AP2: 264000 | AQ2: 2000 | AR2: Contrôle interne / Qualité de service | AS2: Les risques portent sur l'équilibre technique, l'évolution des dépenses de santé, l'adéquation des garanties et l'effet sur la solvabilité. Le risque est fréquent dans les chaînes de gestion volumétriques (cotisations, prestations, flux). | AT2: Risque synthétique fictif mais construit pour ressembler à un registre RCSA d'un OCAM / assureur santé français.
A3: RSH-002 | B3: Souscription & Pilotage Produit | C3: Tarification et pilotage technique santé | D3: Construction des barèmes | E3: Directeur Technique Santé | F3: Directeur Technique / Actuariat | G3: Responsable Actuariat Santé | H3: Conformité / Réglementaire | I3: ACPR / gouvernance produit / information tarifaire | J3: Non-conformité réglementaire ou contractuelle dans Construction des barèmes | K3: Hausse des dépenses optiques/dentaires non intégrée à temps dans le barème et dérive du ratio technique. | L3: Veille réglementaire insuffisante, interprétation partielle des textes, traçabilité insuffisante ou preuves de contrôle manquantes | M3: Sanctions, remédiation, litiges, injonctions, atteinte réputationnelle et augmentation du risque superviseur | N3: Nombre d'exceptions de conformité sur Construction des barèmes | O3: nb | P3: 0 | Q3: 2 | R3: 4 | S3: 3 | T3: 3 | U3: 5 | V3: =T3*U3 -> 15 | W3: =IF(V3>=15,"Critique",IF(V3>=10,"Élevé",IF(V3>=6,"Modéré","Faible"))) -> Critique | X3: Revue de conformité, validation de 2e niveau, piste d'audit et contrôle documentaire | Y3: Détectif | Z3: Trimestrielle | AA3: Faible | AB3: 3 | AC3: 5 | AD3: =AB3*AC3 -> 15 | AE3: =IF(AD3>=15,"Critique",IF(AD3>=10,"Élevé",IF(AD3>=6,"Modéré","Faible"))) -> Critique | AF3: Faible | AG3: =IF(AD3<=IF(AF3="Faible",6,IF(AF3="Modéré",9,12)),"Dans lappétit","Hors appétit") -> Hors appétit | AH3: Réduire | AI3: Mettre à jour la procédure, documenter les preuves de conformité et intégrer construction des barèmes au plan de contrôle permanent. | AJ3: Responsable Actuariat Santé | AK3: 46149 | AL3: Sous contrôle | AM3: 46070 | AN3: Mensuelle | AO3: 2 | AP3: 341000 | AQ3: 2250 | AR3: ACPR / gouvernance produit / information tarifaire | AS3: Les risques portent sur l'équilibre technique, l'évolution des dépenses de santé, l'adéquation des garanties et l'effet sur la solvabilité. Le secteur est fortement encadré par l'ACPR, la DDA, le RGPD et les obligations contractuelles. | AT3: Risque synthétique fictif mais construit pour ressembler à un registre RCSA d'un OCAM / assureur santé français.
A4: RSH-003 | B4: Souscription & Pilotage Produit | C4: Tarification et pilotage technique santé | D4: Construction des barèmes | E4: Directeur Technique Santé | F4: Directeur Technique / Actuariat | G4: Responsable Actuariat Santé | H4: Données / SI / Cyber | I4: RGPD / sécurité / continuité | J4: Altération, indisponibilité ou accès indu aux données et outils supportant Construction des barèmes | K4: Hausse des dépenses optiques/dentaires non intégrée à temps dans le barème et dérive du ratio technique. | L4: Faille de sécurité, habilitations excessives, supervision insuffisante, dette technique ou défaut de reprise | M4: Interruption d'activité, fuite de données sensibles, non-traitement des demandes et coûts de remédiation | N4: Indisponibilité / incidents sécurité liés à Construction des barèmes | O4: nb | P4: 0 | Q4: 1 | R4: 3 | S4: 3 | T4: 3 | U4: 5 | V4: =T4*U4 -> 15 | W4: =IF(V4>=15,"Critique",IF(V4>=10,"Élevé",IF(V4>=6,"Modéré","Faible"))) -> Critique | X4: Gestion des habilitations, sauvegardes, journalisation, supervision et tests PRA/PCA | Y4: Préventif | Z4: Mensuelle | AA4: Moyenne | AB4: 2 | AC4: 5 | AD4: =AB4*AC4 -> 10 | AE4: =IF(AD4>=15,"Critique",IF(AD4>=10,"Élevé",IF(AD4>=6,"Modéré","Faible"))) -> Élevé | AF4: Faible | AG4: =IF(AD4<=IF(AF4="Faible",6,IF(AF4="Modéré",9,12)),"Dans lappétit","Hors appétit") -> Hors appétit | AH4: Mitiger | AI4: Réduire les habilitations, tester la reprise et renforcer la supervision / journalisation sur construction des barèmes. | AJ4: Responsable Actuariat Santé | AK4: 46160 | AL4: Clôturé | AM4: 46064 | AN4: Trimestrielle | AO4: 2 | AP4: 493000 | AQ4: 2500 | AR4: RGPD / sécurité / continuité | AS4: Les risques portent sur l'équilibre technique, l'évolution des dépenses de santé, l'adéquation des garanties et l'effet sur la solvabilité. Les organismes manipulent des données de santé sensibles et dépendent fortement des applications cœur et des flux NOEMIE. | AT4: Risque synthétique fictif mais construit pour ressembler à un registre RCSA d'un OCAM / assureur santé français.
A5: RSH-004 | B5: Souscription & Pilotage Produit | C5: Tarification et pilotage technique santé | D5: Construction des barèmes | E5: Directeur Technique Santé | F5: Directeur Technique / Actuariat | G5: Responsable Actuariat Santé | H5: Fraude / Financier / Partenaire | I5: Fraude / contrôle permanent / gestion déléguée | J5: Sous-tarification, mauvaise anticipation de la dérive médicale ou anti-sélection sur Construction des barèmes | K5: Hausse des dépenses optiques/dentaires non intégrée à temps dans le barème et dérive du ratio technique. | L5: Séparation des tâches insuffisante, détection tardive, données non fiabilisées, contrôles partenaires incomplets ou arbitrages tarifaires inadaptés | M5: Dégradation du ratio combiné santé, baisse de rentabilité, pression sur SCR et besoin de repricing | N5: Montant ou cas atypiques détectés sur Construction des barèmes | O5: nb | P5: 0 | Q5: 3 | R5: 6 | S5: 4 | T5: 2 | U5: 5 | V5: =T5*U5 -> 10 | W5: =IF(V5>=15,"Critique",IF(V5>=10,"Élevé",IF(V5>=6,"Modéré","Faible"))) -> Élevé | X5: Scénarios d'alerte, séparation des tâches, contrôles anti-fraude et revue analytique | Y5: Mixte | Z5: Mensuelle | AA5: Forte | AB5: 1 | AC5: 4 | AD5: =AB5*AC5 -> 4 | AE5: =IF(AD5>=15,"Critique",IF(AD5>=10,"Élevé",IF(AD5>=6,"Modéré","Faible"))) -> Faible | AF5: Faible | AG5: =IF(AD5<=IF(AF5="Faible",6,IF(AF5="Modéré",9,12)),"Dans lappétit","Hors appétit") -> Dans lappétit | AH5: Accepter | AI5: Renforcer les scénarios de détection, la revue analytique et les contrôles ciblés sur construction des barèmes. | AJ5: Responsable Actuariat Santé | AK5: 46171 | AL5: Clôturé | AM5: 46058 | AN5: Semestrielle | AO5: 0 | AP5: 354000 | AQ5: 2750 | AR5: Fraude / contrôle permanent / gestion déléguée | AS5: Les risques portent sur l'équilibre technique, l'évolution des dépenses de santé, l'adéquation des garanties et l'effet sur la solvabilité. Le risque est alimenté par les tiers, les flux financiers, l'anti-sélection et la fraude aux prestations. | AT5: Risque synthétique fictif mais construit pour ressembler à un registre RCSA d'un OCAM / assureur santé français.
A6: RSH-005 | B6: Souscription & Pilotage Produit | C6: Tarification et pilotage technique santé | D6: Révision tarifaire annuelle | E6: Directeur Technique Santé | F6: Directeur Technique / Actuariat | G6: Responsable Pilotage Technique | H6: Opérationnel / Qualité | I6: Contrôle interne / Qualité de service | J6: Erreur d'exécution ou de paramétrage sur Révision tarifaire annuelle | K6: Hausse des dépenses optiques/dentaires non intégrée à temps dans le barème et dérive du ratio technique. | L6: Procédure incomplète, charge mal calibrée, contrôle de 1er niveau insuffisant ou règle métier mal paramétrée | M6: Retards, retraitements, mauvaise qualité de service, hausse du coût de gestion et insatisfaction adhérents/entreprises | N6: Taux d'anomalies opérationnelles sur Révision tarifaire annuelle | O6: % | P6: 1 | Q6: 2.5 | R6: 4 | S6: 2.2 | T6: 3 | U6: 4 | V6: =T6*U6 -> 12 | W6: =IF(V6>=15,"Critique",IF(V6>=10,"Élevé",IF(V6>=6,"Modéré","Faible"))) -> Élevé | X6: Double validation, check-list opératoire, rapprochement quotidien et contrôle de cohérence | Y6: Préventif | Z6: Mensuelle | AA6: Faible | AB6: 3 | AC6: 4 | AD6: =AB6*AC6 -> 12 | AE6: =IF(AD6>=15,"Critique",IF(AD6>=10,"Élevé",IF(AD6>=6,"Modéré","Faible"))) -> Élevé | AF6: Modéré | AG6: =IF(AD6<=IF(AF6="Faible",6,IF(AF6="Modéré",9,12)),"Dans lappétit","Hors appétit") -> Hors appétit | AH6: Réduire | AI6: Formaliser les points de contrôle critiques, renforcer les rapprochements et fiabiliser les règles métier sur révision tarifaire annuelle. | AJ6: Responsable Pilotage Technique | AK6: 46182 | AL6: À lancer | AM6: 46052 | AN6: Trimestrielle | AO6: 3 | AP6: 273000 | AQ6: 2350 | AR6: Contrôle interne / Qualité de service | AS6: Les risques portent sur l'équilibre technique, l'évolution des dépenses de santé, l'adéquation des garanties et l'effet sur la solvabilité. Le risque est fréquent dans les chaînes de gestion volumétriques (cotisations, prestations, flux). | AT6: Risque synthétique fictif mais construit pour ressembler à un registre RCSA d'un OCAM / assureur santé français.
A7: RSH-006 | B7: Souscription & Pilotage Produit | C7: Tarification et pilotage technique santé | D7: Révision tarifaire annuelle | E7: Directeur Technique Santé | F7: Directeur Technique / Actuariat | G7: Responsable Pilotage Technique | H7: Conformité / Réglementaire | I7: ACPR / gouvernance produit / information tarifaire | J7: Non-conformité réglementaire ou contractuelle dans Révision tarifaire annuelle | K7: Hausse des dépenses optiques/dentaires non intégrée à temps dans le barème et dérive du ratio technique. | L7: Veille réglementaire insuffisante, interprétation partielle des textes, traçabilité insuffisante ou preuves de contrôle manquantes | M7: Sanctions, remédiation, litiges, injonctions, atteinte réputationnelle et augmentation du risque superviseur | N7: Nombre d'exceptions de conformité sur Révision tarifaire annuelle | O7: nb | P7: 0 | Q7: 2 | R7: 4 | S7: 2 | T7: 3 | U7: 5 | V7: =T7*U7 -> 15 | W7: =IF(V7>=15,"Critique",IF(V7>=10,"Élevé",IF(V7>=6,"Modéré","Faible"))) -> Critique | X7: Revue de conformité, validation de 2e niveau, piste d'audit et contrôle documentaire | Y7: Détectif | Z7: Trimestrielle | AA7: Moyenne | AB7: 2 | AC7: 5 | AD7: =AB7*AC7 -> 10 | AE7: =IF(AD7>=15,"Critique",IF(AD7>=10,"Élevé",IF(AD7>=6,"Modéré","Faible"))) -> Élevé | AF7: Faible | AG7: =IF(AD7<=IF(AF7="Faible",6,IF(AF7="Modéré",9,12)),"Dans lappétit","Hors appétit") -> Hors appétit | AH7: Réduire | AI7: Mettre à jour la procédure, documenter les preuves de conformité et intégrer révision tarifaire annuelle au plan de contrôle permanent. | AJ7: Responsable Pilotage Technique | AK7: 46193 | AL7: Sous contrôle | AM7: 46046 | AN7: Trimestrielle | AO7: 2 | AP7: 350000 | AQ7: 2600 | AR7: ACPR / gouvernance produit / information tarifaire | AS7: Les risques portent sur l'équilibre technique, l'évolution des dépenses de santé, l'adéquation des garanties et l'effet sur la solvabilité. Le secteur est fortement encadré par l'ACPR, la DDA, le RGPD et les obligations contractuelles. | AT7: Risque synthétique fictif mais construit pour ressembler à un registre RCSA d'un OCAM / assureur santé français.
A8: RSH-007 | B8: Souscription & Pilotage Produit | C8: Tarification et pilotage technique santé | D8: Révision tarifaire annuelle | E8: Directeur Technique Santé | F8: Directeur Technique / Actuariat | G8: Responsable Pilotage Technique | H8: Données / SI / Cyber | I8: RGPD / sécurité / continuité | J8: Altération, indisponibilité ou accès indu aux données et outils supportant Révision tarifaire annuelle | K8: Hausse des dépenses optiques/dentaires non intégrée à temps dans le barème et dérive du ratio technique. | L8: Faille de sécurité, habilitations excessives, supervision insuffisante, dette technique ou défaut de reprise | M8: Interruption d'activité, fuite de données sensibles, non-traitement des demandes et coûts de remédiation | N8: Indisponibilité / incidents sécurité liés à Révision tarifaire annuelle | O8: nb | P8: 0 | Q8: 1 | R8: 3 | S8: 2 | T8: 3 | U8: 5 | V8: =T8*U8 -> 15 | W8: =IF(V8>=15,"Critique",IF(V8>=10,"Élevé",IF(V8>=6,"Modéré","Faible"))) -> Critique | X8: Gestion des habilitations, sauvegardes, journalisation, supervision et tests PRA/PCA | Y8: Préventif | Z8: Mensuelle | AA8: Moyenne | AB8: 2 | AC8: 5 | AD8: =AB8*AC8 -> 10 | AE8: =IF(AD8>=15,"Critique",IF(AD8>=10,"Élevé",IF(AD8>=6,"Modéré","Faible"))) -> Élevé | AF8: Faible | AG8: =IF(AD8<=IF(AF8="Faible",6,IF(AF8="Modéré",9,12)),"Dans lappétit","Hors appétit") -> Hors appétit | AH8: Mitiger | AI8: Réduire les habilitations, tester la reprise et renforcer la supervision / journalisation sur révision tarifaire annuelle. | AJ8: Responsable Pilotage Technique | AK8: 46204 | AL8: Clôturé | AM8: 46040 | AN8: Trimestrielle | AO8: 2 | AP8: 505000 | AQ8: 2850 | AR8: RGPD / sécurité / continuité | AS8: Les risques portent sur l'équilibre technique, l'évolution des dépenses de santé, l'adéquation des garanties et l'effet sur la solvabilité. Les organismes manipulent des données de santé sensibles et dépendent fortement des applications cœur et des flux NOEMIE. | AT8: Risque synthétique fictif mais construit pour ressembler à un registre RCSA d'un OCAM / assureur santé français.
A9: RSH-008 | B9: Souscription & Pilotage Produit | C9: Tarification et pilotage technique santé | D9: Révision tarifaire annuelle | E9: Directeur Technique Santé | F9: Directeur Technique / Actuariat | G9: Responsable Pilotage Technique | H9: Fraude / Financier / Partenaire | I9: Fraude / contrôle permanent / gestion déléguée | J9: Sous-tarification, mauvaise anticipation de la dérive médicale ou anti-sélection sur Révision tarifaire annuelle | K9: Hausse des dépenses optiques/dentaires non intégrée à temps dans le barème et dérive du ratio technique. | L9: Séparation des tâches insuffisante, détection tardive, données non fiabilisées, contrôles partenaires incomplets ou arbitrages tarifaires inadaptés | M9: Dégradation du ratio combiné santé, baisse de rentabilité, pression sur SCR et besoin de repricing | N9: Montant ou cas atypiques détectés sur Révision tarifaire annuelle | O9: nb | P9: 0 | Q9: 3 | R9: 6 | S9: 5 | T9: 3 | U9: 5 | V9: =T9*U9 -> 15 | W9: =IF(V9>=15,"Critique",IF(V9>=10,"Élevé",IF(V9>=6,"Modéré","Faible"))) -> Critique | X9: Scénarios d'alerte, séparation des tâches, contrôles anti-fraude et revue analytique | Y9: Mixte | Z9: Mensuelle | AA9: Moyenne | AB9: 2 | AC9: 5 | AD9: =AB9*AC9 -> 10 | AE9: =IF(AD9>=15,"Critique",IF(AD9>=10,"Élevé",IF(AD9>=6,"Modéré","Faible"))) -> Élevé | AF9: Faible | AG9: =IF(AD9<=IF(AF9="Faible",6,IF(AF9="Modéré",9,12)),"Dans lappétit","Hors appétit") -> Hors appétit | AH9: Réduire | AI9: Renforcer les scénarios de détection, la revue analytique et les contrôles ciblés sur révision tarifaire annuelle. | AJ9: Responsable Pilotage Technique | AK9: 46215 | AL9: À lancer | AM9: 46034 | AN9: Trimestrielle | AO9: 2 | AP9: 521000 | AQ9: 3100 | AR9: Fraude / contrôle permanent / gestion déléguée | AS9: Les risques portent sur l'équilibre technique, l'évolution des dépenses de santé, l'adéquation des garanties et l'effet sur la solvabilité. Le risque est alimenté par les tiers, les flux financiers, l'anti-sélection et la fraude aux prestations. | AT9: Risque synthétique fictif mais construit pour ressembler à un registre RCSA d'un OCAM / assureur santé français.
A10: RSH-009 | B10: Souscription & Pilotage Produit | C10: Tarification et pilotage technique santé | D10: Suivi du ratio prestations/cotisations | E10: Directeur Technique Santé | F10: Directeur Technique / Actuariat | G10: Responsable Contrôle Technique | H10: Opérationnel / Qualité | I10: Contrôle interne / Qualité de service | J10: Erreur d'exécution ou de paramétrage sur Suivi du ratio prestations/cotisations | K10: Hausse des dépenses optiques/dentaires non intégrée à temps dans le barème et dérive du ratio technique. | L10: Procédure incomplète, charge mal calibrée, contrôle de 1er niveau insuffisant ou règle métier mal paramétrée | M10: Retards, retraitements, mauvaise qualité de service, hausse du coût de gestion et insatisfaction adhérents/entreprises | N10: Taux d'anomalies opérationnelles sur Suivi du ratio prestations/cotisations | O10: % | P10: 1 | Q10: 2.5 | R10: 4 | S10: 2.7 | T10: 4 | U10: 4 | V10: =T10*U10 -> 16 | W10: =IF(V10>=15,"Critique",IF(V10>=10,"Élevé",IF(V10>=6,"Modéré","Faible"))) -> Critique | X10: Double validation, check-list opératoire, rapprochement quotidien et contrôle de cohérence | Y10: Préventif | Z10: Mensuelle | AA10: Forte | AB10: 2 | AC10: 3 | AD10: =AB10*AC10 -> 6 | AE10: =IF(AD10>=15,"Critique",IF(AD10>=10,"Élevé",IF(AD10>=6,"Modéré","Faible"))) -> Modéré | AF10: Modéré | AG10: =IF(AD10<=IF(AF10="Faible",6,IF(AF10="Modéré",9,12)),"Dans lappétit","Hors appétit") -> Dans lappétit | AH10: Accepter | AI10: Formaliser les points de contrôle critiques, renforcer les rapprochements et fiabiliser les règles métier sur suivi du ratio prestations/cotisations. | AJ10: Responsable Contrôle Technique | AK10: 46226 | AL10: En cours | AM10: 46028 | AN10: Semestrielle | AO10: 3 | AP10: 370000 | AQ10: 2700 | AR10: Contrôle interne / Qualité de service | AS10: Les risques portent sur l'équilibre technique, l'évolution des dépenses de santé, l'adéquation des garanties et l'effet sur la solvabilité. Le risque est fréquent dans les chaînes de gestion volumétriques (cotisations, prestations, flux). | AT10: Risque synthétique fictif mais construit pour ressembler à un registre RCSA d'un OCAM / assureur santé français.
A11: RSH-010 | B11: Souscription & Pilotage Produit | C11: Tarification et pilotage technique santé | D11: Suivi du ratio prestations/cotisations | E11: Directeur Technique Santé | F11: Directeur Technique / Actuariat | G11: Responsable Contrôle Technique | H11: Conformité / Réglementaire | I11: ACPR / gouvernance produit / information tarifaire | J11: Non-conformité réglementaire ou contractuelle dans Suivi du ratio prestations/cotisations | K11: Hausse des dépenses optiques/dentaires non intégrée à temps dans le barème et dérive du ratio technique. | L11: Veille réglementaire insuffisante, interprétation partielle des textes, traçabilité insuffisante ou preuves de contrôle manquantes | M11: Sanctions, remédiation, litiges, injonctions, atteinte réputationnelle et augmentation du risque superviseur | N11: Nombre d'exceptions de conformité sur Suivi du ratio prestations/cotisations | O11: nb | P11: 0 | Q11: 2 | R11: 4 | S11: 2 | T11: 3 | U11: 5 | V11: =T11*U11 -> 15 | W11: =IF(V11>=15,"Critique",IF(V11>=10,"Élevé",IF(V11>=6,"Modéré","Faible"))) -> Critique | X11: Revue de conformité, validation de 2e niveau, piste d'audit et contrôle documentaire | Y11: Détectif | Z11: Trimestrielle | AA11: Forte | AB11: 2 | AC11: 4 | AD11: =AB11*AC11 -> 8 | AE11: =IF(AD11>=15,"Critique",IF(AD11>=10,"Élevé",IF(AD11>=6,"Modéré","Faible"))) -> Modéré | AF11: Faible | AG11: =IF(AD11<=IF(AF11="Faible",6,IF(AF11="Modéré",9,12)),"Dans lappétit","Hors appétit") -> Hors appétit | AH11: Réduire | AI11: Mettre à jour la procédure, documenter les preuves de conformité et intégrer suivi du ratio prestations/cotisations au plan de contrôle permanent. | AJ11: Responsable Contrôle Technique | AK11: 46237 | AL11: Sous contrôle | AM11: 46022 | AN11: Semestrielle | AO11: 1 | AP11: 359000 | AQ11: 2950 | AR11: ACPR / gouvernance produit / information tarifaire | AS11: Les risques portent sur l'équilibre technique, l'évolution des dépenses de santé, l'adéquation des garanties et l'effet sur la solvabilité. Le secteur est fortement encadré par l'ACPR, la DDA, le RGPD et les obligations contractuelles. | AT11: Risque synthétique fictif mais construit pour ressembler à un registre RCSA d'un OCAM / assureur santé français.
A12: RSH-011 | B12: Souscription & Pilotage Produit | C12: Tarification et pilotage technique santé | D12: Suivi du ratio prestations/cotisations | E12: Directeur Technique Santé | F12: Directeur Technique / Actuariat | G12: Responsable Contrôle Technique | H12: Données / SI / Cyber | I12: RGPD / sécurité / continuité | J12: Altération, indisponibilité ou accès indu aux données et outils supportant Suivi du ratio prestations/cotisations | K12: Hausse des dépenses optiques/dentaires non intégrée à temps dans le barème et dérive du ratio technique. | L12: Faille de sécurité, habilitations excessives, supervision insuffisante, dette technique ou défaut de reprise | M12: Interruption d'activité, fuite de données sensibles, non-traitement des demandes et coûts de remédiation | N12: Indisponibilité / incidents sécurité liés à Suivi du ratio prestations/cotisations | O12: nb | P12: 0 | Q12: 1 | R12: 3 | S12: 1 | T12: 3 | U12: 5 | V12: =T12*U12 -> 15 | W12: =IF(V12>=15,"Critique",IF(V12>=10,"Élevé",IF(V12>=6,"Modéré","Faible"))) -> Critique | X12: Gestion des habilitations, sauvegardes, journalisation, supervision et tests PRA/PCA | Y12: Préventif | Z12: Mensuelle | AA12: Faible | AB12: 3 | AC12: 5 | AD12: =AB12*AC12 -> 15 | AE12: =IF(AD12>=15,"Critique",IF(AD12>=10,"Élevé",IF(AD12>=6,"Modéré","Faible"))) -> Critique | AF12: Faible | AG12: =IF(AD12<=IF(AF12="Faible",6,IF(AF12="Modéré",9,12)),"Dans lappétit","Hors appétit") -> Hors appétit | AH12: Mitiger | AI12: Réduire les habilitations, tester la reprise et renforcer la supervision / journalisation sur suivi du ratio prestations/cotisations. | AJ12: Responsable Contrôle Technique | AK12: 46248 | AL12: Clôturé | AM12: 46016 | AN12: Mensuelle | AO12: 2 | AP12: 518000 | AQ12: 3200 | AR12: RGPD / sécurité / continuité | AS12: Les risques portent sur l'équilibre technique, l'évolution des dépenses de santé, l'adéquation des garanties et l'effet sur la solvabilité. Les organismes manipulent des données de santé sensibles et dépendent fortement des applications cœur et des flux NOEMIE. | AT12: Risque synthétique fictif mais construit pour ressembler à un registre RCSA d'un OCAM / assureur santé français.
A13: RSH-012 | B13: Souscription & Pilotage Produit | C13: Tarification et pilotage technique santé | D13: Suivi du ratio prestations/cotisations | E13: Directeur Technique Santé | F13: Directeur Technique / Actuariat | G13: Responsable Contrôle Technique | H13: Fraude / Financier / Partenaire | I13: Fraude / contrôle permanent / gestion déléguée | J13: Sous-tarification, mauvaise anticipation de la dérive médicale ou anti-sélection sur Suivi du ratio prestations/cotisations | K13: Hausse des dépenses optiques/dentaires non intégrée à temps dans le barème et dérive du ratio technique. | L13: Séparation des tâches insuffisante, détection tardive, données non fiabilisées, contrôles partenaires incomplets ou arbitrages tarifaires inadaptés | M13: Dégradation du ratio combiné santé, baisse de rentabilité, pression sur SCR et besoin de repricing | N13: Montant ou cas atypiques détectés sur Suivi du ratio prestations/cotisations | O13: nb | P13: 0 | Q13: 3 | R13: 6 | S13: 4 | T13: 3 | U13: 5 | V13: =T13*U13 -> 15 | W13: =IF(V13>=15,"Critique",IF(V13>=10,"Élevé",IF(V13>=6,"Modéré","Faible"))) -> Critique | X13: Scénarios d'alerte, séparation des tâches, contrôles anti-fraude et revue analytique | Y13: Mixte | Z13: Mensuelle | AA13: Faible | AB13: 3 | AC13: 5 | AD13: =AB13*AC13 -> 15 | AE13: =IF(AD13>=15,"Critique",IF(AD13>=10,"Élevé",IF(AD13>=6,"Modéré","Faible"))) -> Critique | AF13: Faible | AG13: =IF(AD13<=IF(AF13="Faible",6,IF(AF13="Modéré",9,12)),"Dans lappétit","Hors appétit") -> Hors appétit | AH13: Réduire | AI13: Renforcer les scénarios de détection, la revue analytique et les contrôles ciblés sur suivi du ratio prestations/cotisations. | AJ13: Responsable Contrôle Technique | AK13: 46259 | AL13: À lancer | AM13: 46010 | AN13: Mensuelle | AO13: 2 | AP13: 533000 | AQ13: 3450 | AR13: Fraude / contrôle permanent / gestion déléguée | AS13: Les risques portent sur l'équilibre technique, l'évolution des dépenses de santé, l'adéquation des garanties et l'effet sur la solvabilité. Le risque est alimenté par les tiers, les flux financiers, l'anti-sélection et la fraude aux prestations. | AT13: Risque synthétique fictif mais construit pour ressembler à un registre RCSA d'un OCAM / assureur santé français.
... A121: RSH-120 | B121: SI, Data & Sécurité | C121: Applications cœur santé et cybersécurité | D121: Détection et réponse aux incidents cyber | E121: DSI Assurance Santé | F121: RSSI / DSI | G121: RSSI Opérations | H121: Fraude / Financier / Partenaire | I121: Fraude / contrôle permanent / gestion déléguée | J121: Fraude, surfacturation, anti-sélection ou perte financière liée à Détection et réponse aux incidents cyber | K121: Cyberincident ou changement applicatif dégradant la liquidation, la relation client et l'accès aux données sensibles. | L121: Séparation des tâches insuffisante, détection tardive, données non fiabilisées, contrôles partenaires incomplets ou arbitrages tarifaires inadaptés | M121: Pertes financières, dérive du ratio technique, litiges partenaires, hausse des provisions et fragilisation de la marge | N121: Montant ou cas atypiques détectés sur Détection et réponse aux incidents cyber | O121: nb | P121: 0 | Q121: 3 | R121: 6 | S121: 3 | T121: 3 | U121: 5 | V121: =T121*U121 -> 15 | W121: =IF(V121>=15,"Critique",IF(V121>=10,"Élevé",IF(V121>=6,"Modéré","Faible"))) -> Critique | X121: Scénarios d'alerte, séparation des tâches, contrôles anti-fraude et revue analytique | Y121: Mixte | Z121: Mensuelle | AA121: Faible | AB121: 3 | AC121: 5 | AD121: =AB121*AC121 -> 15 | AE121: =IF(AD121>=15,"Critique",IF(AD121>=10,"Élevé",IF(AD121>=6,"Modéré","Faible"))) -> Critique | AF121: Faible | AG121: =IF(AD121<=IF(AF121="Faible",6,IF(AF121="Modéré",9,12)),"Dans lappétit","Hors appétit") -> Hors appétit | AH121: Réduire | AI121: Renforcer les scénarios de détection, la revue analytique et les contrôles ciblés sur détection et réponse aux incidents cyber. | AJ121: RSSI Opérations | AK121: 46247 | AL121: À lancer | AM121: 46082 | AN121: Mensuelle | AO121: 2 | AP121: 743000 | AQ121: 10450 | AR121: Fraude / contrôle permanent / gestion déléguée | AS121: Les risques concernent l'indisponibilité des applicatifs, la cybersécurité, les changements et la résilience opérationnelle. Le risque est alimenté par les tiers, les flux financiers, l'anti-sélection et la fraude aux prestations. | AT121: Risque synthétique fictif mais construit pour ressembler à un registre RCSA d'un OCAM / assureur santé français.

Sheet Synthese
A1: Synthèse de la cartographie – Assurance santé
A3: Indicateurs globaux
A5: Indicateur | B5: Valeur
A6: Nombre total de risques | B6: =COUNTA(Registre_Risques!A:A)-1 -> 120
A7: Nombre de directions | B7: 5
A8: Nombre de processus | B8: 11
A9: Risques bruts critiques | B9: =COUNTIF(Registre_Risques!W:W,"Critique") -> 75
A10: Risques résiduels critiques | B10: =COUNTIF(Registre_Risques!AE:AE,"Critique") -> 30
A11: Risques hors appétit | B11: =COUNTIF(Registre_Risques!AG:AG,"Hors appétit") -> 91
A12: Pertes synthétiques 12m (EUR) | B12: =SUM(Registre_Risques!AP:AP) -> 60362000
A13: Population potentiellement impactable | B13: =SUM(Registre_Risques!AQ:AQ) -> 812280
A16: Répartition par direction
A17: Direction | B17: Nb risques | C17: Score brut moyen | D17: Score résiduel moyen | E17: Hors appétit
A18: Finance, Risques & Conformité | B18: =COUNTIF(Registre_Risques!B:B,A18) -> 32 | C18: =AVERAGEIF(Registre_Risques!B:B,A18,Registre_Risques!V:V) -> 13.6875 | D18: =AVERAGEIF(Registre_Risques!B:B,A18,Registre_Risques!AD:AD) -> 9.90625 | E18: =COUNTIFS(Registre_Risques!B:B,A18,Registre_Risques!AG:AG,"Hors appétit") -> 23
A19: Prestations & Relation Adhérents | B19: =COUNTIF(Registre_Risques!B:B,A19) -> 20 | C19: =AVERAGEIF(Registre_Risques!B:B,A19,Registre_Risques!V:V) -> 15.85 | D19: =AVERAGEIF(Registre_Risques!B:B,A19,Registre_Risques!AD:AD) -> 12.15 | E19: =COUNTIFS(Registre_Risques!B:B,A19,Registre_Risques!AG:AG,"Hors appétit") -> 17
A20: Réseau de soins & Partenaires | B20: =COUNTIF(Registre_Risques!B:B,A20) -> 20 | C20: =AVERAGEIF(Registre_Risques!B:B,A20,Registre_Risques!V:V) -> 15.1 | D20: =AVERAGEIF(Registre_Risques!B:B,A20,Registre_Risques!AD:AD) -> 11.3 | E20: =COUNTIFS(Registre_Risques!B:B,A20,Registre_Risques!AG:AG,"Hors appétit") -> 16
A21: SI, Data & Sécurité | B21: =COUNTIF(Registre_Risques!B:B,A21) -> 24 | C21: =AVERAGEIF(Registre_Risques!B:B,A21,Registre_Risques!V:V) -> 14.375 | D21: =AVERAGEIF(Registre_Risques!B:B,A21,Registre_Risques!AD:AD) -> 10.375 | E21: =COUNTIFS(Registre_Risques!B:B,A21,Registre_Risques!AG:AG,"Hors appétit") -> 18
A22: Souscription & Pilotage Produit | B22: =COUNTIF(Registre_Risques!B:B,A22) -> 24 | C22: =AVERAGEIF(Registre_Risques!B:B,A22,Registre_Risques!V:V) -> 13.583333 | D22: =AVERAGEIF(Registre_Risques!B:B,A22,Registre_Risques!AD:AD) -> 9.9583333 | E22: =COUNTIFS(Registre_Risques!B:B,A22,Registre_Risques!AG:AG,"Hors appétit") -> 17
A25: Top 10 processus (liste)
A26: Processus | B26: Nb risques | C26: Critiques résiduels | D26: Pertes 12m
A27: Applications cœur santé et cybersécurité | B27: =COUNTIF(Registre_Risques!C:C,A27) -> 12 | C27: =COUNTIFS(Registre_Risques!C:C,A27,Registre_Risques!AE:AE,"Critique") -> 3 | D27: =SUMIF(Registre_Risques!C:C,A27,Registre_Risques!AP:AP) -> 7195000
A28: Conformité, distribution et lutte anti-fraude | B28: =COUNTIF(Registre_Risques!C:C,A28) -> 12 | C28: =COUNTIFS(Registre_Risques!C:C,A28,Registre_Risques!AE:AE,"Critique") -> 4 | D28: =SUMIF(Registre_Risques!C:C,A28,Registre_Risques!AP:AP) -> 7005000
A29: Conventionnement et contrôle des partenaires de santé | B29: =COUNTIF(Registre_Risques!C:C,A29) -> 8 | C29: =COUNTIFS(Registre_Risques!C:C,A29,Registre_Risques!AE:AE,"Critique") -> 0 | D29: =SUMIF(Registre_Risques!C:C,A29,Registre_Risques!AP:AP) -> 3694000
A30: Encaissement des cotisations et recouvrement | B30: =COUNTIF(Registre_Risques!C:C,A30) -> 12 | C30: =COUNTIFS(Registre_Risques!C:C,A30,Registre_Risques!AE:AE,"Critique") -> 1 | D30: =SUMIF(Registre_Risques!C:C,A30,Registre_Risques!AP:AP) -> 5794000
A31: Gestion des données de santé et RGPD | B31: =COUNTIF(Registre_Risques!C:C,A31) -> 12 | C31: =COUNTIFS(Registre_Risques!C:C,A31,Registre_Risques!AE:AE,"Critique") -> 4 | D31: =SUMIF(Registre_Risques!C:C,A31,Registre_Risques!AP:AP) -> 6781000
A32: Gestion des prestations et remboursements | B32: =COUNTIF(Registre_Risques!C:C,A32) -> 12 | C32: =COUNTIFS(Registre_Risques!C:C,A32,Registre_Risques!AE:AE,"Critique") -> 7 | D32: =SUMIF(Registre_Risques!C:C,A32,Registre_Risques!AP:AP) -> 6479000
A33: Relation adhérents et réclamations | B33: =COUNTIF(Registre_Risques!C:C,A33) -> 8 | C33: =COUNTIFS(Registre_Risques!C:C,A33,Registre_Risques!AE:AE,"Critique") -> 0 | D33: =SUMIF(Registre_Risques!C:C,A33,Registre_Risques!AP:AP) -> 3432000
A34: Solvabilité II, ORSA et reportings prudentiels | B34: =COUNTIF(Registre_Risques!C:C,A34) -> 8 | C34: =COUNTIFS(Registre_Risques!C:C,A34,Registre_Risques!AE:AE,"Critique") -> 0 | D34: =SUMIF(Registre_Risques!C:C,A34,Registre_Risques!AP:AP) -> 3845000
A35: Souscription individuelle et collective | B35: =COUNTIF(Registre_Risques!C:C,A35) -> 12 | C35: =COUNTIFS(Registre_Risques!C:C,A35,Registre_Risques!AE:AE,"Critique") -> 2 | D35: =SUMIF(Registre_Risques!C:C,A35,Registre_Risques!AP:AP) -> 4745000
A36: Tarification et pilotage technique santé | B36: =COUNTIF(Registre_Risques!C:C,A36) -> 12 | C36: =COUNTIFS(Registre_Risques!C:C,A36,Registre_Risques!AE:AE,"Critique") -> 3 | D36: =SUMIF(Registre_Risques!C:C,A36,Registre_Risques!AP:AP) -> 4881000
